ksiterate.py
ksiterate-1.2.dist-info/licenses/LICENSE
ksiterate-1.2.dist-info/METADATA
ksiterate-1.2.dist-info/WHEEL
ksiterate-1.2.dist-info/top_level.txt
ksiterate-1.2.dist-info/RECORD
