Metadata-Version: 2.4
Name: ksiterate
Version: 1.2
Summary: Module for iteration over product of given parameter values
Author: Konrad Sakowski
Platform: any
Classifier: Programming Language :: Python :: 3
Classifier: License :: OSI Approved :: Apache Software License
Classifier: Operating System :: OS Independent
Requires-Python: >=3.6
License-File: LICENSE
Dynamic: author
Dynamic: classifier
Dynamic: description
Dynamic: description-content-type
Dynamic: license-file
Dynamic: platform
Dynamic: requires-python
Dynamic: summary
